{
    "$schema" : "https://json-schema.axonivy.com/market/10.0.2/meta.json",
    "id" : "docker-connector",
    "name" : "Docker",
    "names" : [
        {
            "locale" : "en",
            "value" : "Docker"
        },
        {
            "locale" : "de",
            "value" : "Docker"
        }
    ],
    "description" : "Create, start, stop, remove Docker containers directly from your business processes.",
    "descriptions" : [
        {
            "locale" : "en",
            "value" : "Create, start, stop, remove Docker containers directly from your business processes."
        },
        {
            "locale" : "de",
            "value" : "Du kannst Docker-Container direkt aus deinen Geschäftsprozessen erstellen, starten, stoppen und entfernen."
        }
    ],
    "type" : "connector",
    "platformReview" : "4.5",
    "sourceUrl" : "https://github.com/axonivy-market/docker-connector",
    "statusBadgeUrl" : "https://github.com/axonivy-market/docker-connector/actions/workflows/ci.yml/badge.svg",
    "language" : "English",
    "industry" : "Cross-Industry",
    "tags" : [
        "container"
    ],
    "mavenArtifacts" : [
        {
            "repoUrl" : "https://maven.axonivy.com",
            "name" : "Docker Connector",
            "groupId" : "com.axonivy.market",
            "artifactId" : "docker-connector-product",
            "type" : "zip"
        },
        {
            "key" : "docker-connector",
            "name" : "Docker Demo App",
            "groupId" : "com.axonivy.market",
            "artifactId" : "docker-connector-demo-app",
            "type" : "zip"
        }
    ]
}